kama_prom_plugin/__init__.py
kama_prom_plugin/consts.py
kama_prom_plugin/plugin.py
kama_prom_plugin/assets/locate-existing-grafana.md
kama_prom_plugin/assets/locate-existing-server.md
kama_prom_plugin/assets/plugin-intro.md
kama_prom_plugin/descriptors/helpers/deployment_mem_cpu.yaml
kama_prom_plugin/descriptors/operation/locate-prometheus/fields.yaml
kama_prom_plugin/descriptors/operation/locate-prometheus/operation.yaml
kama_prom_plugin/descriptors/variables/grafana-variables.yaml
kama_prom_plugin/descriptors/variables/prom-variables.yaml
kama_prom_plugin/models/__init__.py
kama_prom_plugin/models/grafana_state_supplier.py
kama_prom_plugin/models/prom_client.py
kama_prom_plugin/models/prom_data_supplier.py
kama_prom_plugin/models/prom_matrix_to_timeseries_supplier.py
kama_prom_plugin/models/prom_state_supplier.py
kama_prom_plugin/models/prom_utils.py
kama_prom_plugin/models/prom_vector_to_groups_provider.py
kama_prom_plugin/models/types.py
kama_prom_plugin-0.0.5.dist-info/METADATA
kama_prom_plugin-0.0.5.dist-info/WHEEL
kama_prom_plugin-0.0.5.dist-info/top_level.txt
kama_prom_plugin-0.0.5.dist-info/RECORD
